oktaloginwrapper/OktaLoginWrapper.py
oktaloginwrapper/__init__.py
oktaloginwrapper-0.2.2.dist-info/LICENSE
oktaloginwrapper-0.2.2.dist-info/METADATA
oktaloginwrapper-0.2.2.dist-info/WHEEL
oktaloginwrapper-0.2.2.dist-info/top_level.txt
oktaloginwrapper-0.2.2.dist-info/RECORD
