Metadata-Version: 2.1
Name: oktaloginwrapper
Version: 0.2.2
Summary: Okta login made easy from the command line without API token
Home-page: https://github.com/B-Souty/OktaLoginWrapper
Author: B-Souty
Author-email: benjamin.souty@gmail.com
License: MIT
Platform: UNKNOWN
Classifier: Programming Language :: Python :: 3
Classifier: License :: OSI Approved :: MIT License
Classifier: Operating System :: OS Independent
Requires-Dist: lxml
Requires-Dist: requests
